email_mcp_server.py
mbrug/__init__.py
mbrug/email_mcp_server.py
mbrug_email_mcp_server-0.1.0.dist-info/licenses/LICENSE
mbrug_email_mcp_server-0.1.0.dist-info/METADATA
mbrug_email_mcp_server-0.1.0.dist-info/WHEEL
mbrug_email_mcp_server-0.1.0.dist-info/entry_points.txt
mbrug_email_mcp_server-0.1.0.dist-info/top_level.txt
mbrug_email_mcp_server-0.1.0.dist-info/RECORD
