Metadata-Version: 2.4
Name: mbrug-email-mcp-server
Version: 0.1.0
Summary: Email MCP Server for Amazon Q CLI
Author-email: mbrug <mbrug@example.com>
Project-URL: Homepage, https://github.com/mbrug/email-mcp-server
Project-URL: Bug Tracker, https://github.com/mbrug/email-mcp-server/issues
Classifier: Programming Language :: Python :: 3
Classifier: License :: OSI Approved :: MIT License
Classifier: Operating System :: OS Independent
Requires-Python: >=3.6
License-File: LICENSE
Requires-Dist: google-auth-oauthlib
Requires-Dist: google-auth
Requires-Dist: google-api-python-client
Dynamic: license-file
Dynamic: requires-python
